TopLoader/__init__.py
TopLoader-0.0.1.dist-info/LICENSE.txt
TopLoader-0.0.1.dist-info/METADATA
TopLoader-0.0.1.dist-info/WHEEL
TopLoader-0.0.1.dist-info/top_level.txt
TopLoader-0.0.1.dist-info/RECORD
