Metadata-Version: 2.1
Name: TopLoader
Version: 0.0.1
Summary: Load Julia Modules -- The Easy way!
Home-page: https://github.com/emmettgb/TopLoader
Author: Emmett Boudreau
Author-email: emmettgb@gmail.com
License: UNKNOWN
Platform: UNKNOWN
Classifier: Programming Language :: Python :: 3
Classifier: License :: OSI Approved :: MIT License
Classifier: Operating System :: OS Independent
Requires-Python: >=3.6
